markdown_includecustom/__init__.py
markdown_includecustom/includecustom.py
markdown_includecustom-0.1.6.dist-info/METADATA
markdown_includecustom-0.1.6.dist-info/WHEEL
markdown_includecustom-0.1.6.dist-info/top_level.txt
markdown_includecustom-0.1.6.dist-info/RECORD
